<?xml version="1.0" encoding="UTF-8"?>


<!DOCTYPE hibernate-mapping PUBLIC "-//Hibernate/Hibernate Mapping DTD 3.0//EN"

"http://hibernate.sourceforge.net/hibernate-mapping-3.0.dtd">

<hibernate-mapping>
	<class name="bean.Article" table="article" lazy="false">
		<id name="id" column="id" type="long">
			<generator class="increment" />

		</id>

		<property name="title" column="title" type="string"></property>
		<property name="content" column="content" type="string"></property>



	</class>
</hibernate-mapping>
